CHANGELOG
LICENSE
MANIFEST.in
README.rst
setup.py
tox.ini
docs/Makefile
docs/climate.rst
docs/conf.py
docs/index.rst
docs/indicators.rst
docs/make.bat
wbpy/__init__.py
wbpy/climate.py
wbpy/indicators.py
wbpy/non_ISO_region_codes.json
wbpy/utils.py
wbpy.egg-info/PKG-INFO
wbpy.egg-info/SOURCES.txt
wbpy.egg-info/dependency_links.txt
wbpy.egg-info/requires.txt
wbpy.egg-info/top_level.txt
wbpy/tests/__init__.py
wbpy/tests/climate_data.py
wbpy/tests/indicator_data.py
wbpy/tests/test_climate.py
wbpy/tests/test_indicators.py
wbpy/tests/test_utils.py