Metadata-Version: 1.1
Name: wbpy
Version: 2.0.1
Summary: A Python interface to the World Bank Indicators and Climate APIs
Home-page: https://github.com/mattduck/wbpy
Author: Matthew Duck
Author-email: matt@mattduck.com
License: MIT
Platform: UNKNOWN
Classifier: Development Status :: 4 - Beta
Classifier: Intended Audience :: Developers
Classifier: Intended Audience :: Science/Research
Classifier: License :: OSI Approved :: MIT License
Classifier: Operating System :: OS Independent
Classifier: Programming Language :: Python
Classifier: Programming Language :: Python :: 3
Classifier: Topic :: Scientific/Engineering
Provides: wbpy
